cert_pruner/__init__.py
cert_pruner/cli.py
cert_pruner/pruner.py
cert_pruner-1.1.1.dist-info/METADATA
cert_pruner-1.1.1.dist-info/WHEEL
cert_pruner-1.1.1.dist-info/entry_points.txt
cert_pruner-1.1.1.dist-info/top_level.txt
cert_pruner-1.1.1.dist-info/RECORD
