Metadata-Version: 2.1
Name: cert-pruner
Version: 1.1.1
Summary: Prune IAM Server Certificates that are not attached to an ELB
Home-page: https://github.com/GESkunkworks/cert-pruner
Author: Michael Palmer
Author-email: github@michaeldpalmer.com
License: UNKNOWN
Keywords: certificate cert prune delete iam aws
Platform: UNKNOWN
Classifier: Programming Language :: Python :: 2.7
Classifier: Programming Language :: Python :: 3.6
Classifier: Development Status :: 4 - Beta
Classifier: Topic :: Utilities
Requires-Dist: boto3 (~=1.7.16)
Requires-Dist: pytz (~=2018.4)
Requires-Dist: setuptools-scm (~=3.1.0)
